{"error": true, "size": [1920, 1080], "name": "Gwetome Academy", "version": "1.0", "location": {"label": {"pro": ["game/script.rpy", 148], "DefaultQuestion": ["game/script.rpy", 165], "Questions_mc": ["game/script.rpy", 186], "Questions_mc.Question_What": ["game/script.rpy", 187], "Questions_mc.Answer_Nothing": ["game/script.rpy", 188], "Questions_mc.Answer_Hi": ["game/script.rpy", 191], "p": ["game/script.rpy", 199], "riri": ["game/script.rpy", 203], "start": ["game/script.rpy", 339], "s2": ["game/script.rpy", 376], "s3": ["game/script.rpy", 401], "s4": ["game/script.rpy", 420], "s5": ["game/script.rpy", 455], "s6": ["game/script.rpy", 519], "s7": ["game/script.rpy", 558], "s8": ["game/script.rpy", 578], "s9": ["game/script.rpy", 592], "s10": ["game/script.rpy", 623], "s11": ["game/script.rpy", 658], "s12": ["game/script.rpy", 675], "s13": ["game/script.rpy", 681], "s14": ["game/script.rpy", 721], "s15": ["game/script.rpy", 791], "s16": ["game/script.rpy", 835], "s17": ["game/script.rpy", 856], "s18": ["game/script.rpy", 898], "s18_1": ["game/script.rpy", 909], "s18_2": ["game/script.rpy", 917], "s18_3": ["game/script.rpy", 923], "s18_4": ["game/script.rpy", 942], "s19": ["game/script.rpy", 948], "s20": ["game/script.rpy", 960], "s21": ["game/script.rpy", 968], "s22": ["game/script.rpy", 982], "s23": ["game/script.rpy", 1010], "s24": ["game/script.rpy", 1012], "s25": ["game/script.rpy", 1086], "s26": ["game/script.rpy", 1094], "s27": ["game/script.rpy", 1142], "s28": ["game/script.rpy", 1166], "s29": ["game/script.rpy", 1209], "s30": ["game/script.rpy", 1241], "s31": ["game/script.rpy", 1259], "s32": ["game/script.rpy", 1287], "s33": ["game/script.rpy", 1307], "s34": ["game/script.rpy", 1329], "s35": ["game/script.rpy", 1351], "s36": ["game/script.rpy", 1365], "s37": ["game/script.rpy", 1379], "s38": ["game/script.rpy", 1403], "s39": ["game/script.rpy", 1463], "s40": ["game/script.rpy", 1510], "s41": ["game/script.rpy", 1568], "s42": ["game/script.rpy", 1580], "s43": ["game/script.rpy", 1598], "s44": ["game/script.rpy", 1624], "s45": ["game/script.rpy", 1656], "s46": ["game/script.rpy", 1682], "s47": ["game/script.rpy", 1720], "s48": ["game/script.rpy", 1752], "s49": ["game/script.rpy", 1795], "s50": ["game/script.rpy", 1835], "s51": ["game/script.rpy", 1897], "s52": ["game/script.rpy", 1945], "s53": ["game/script.rpy", 1986], "s54": ["game/script.rpy", 2012], "s55": ["game/script.rpy", 2034], "s56": ["game/script.rpy", 2092], "s57": ["game/script.rpy", 2117], "s58": ["game/script.rpy", 2147], "s59": ["game/script.rpy", 2173], "s60": ["game/script.rpy", 2185], "s61": ["game/script.rpy", 2231], "s62": ["game/script.rpy", 2267], "s63": ["game/script.rpy", 2303], "s64": ["game/script.rpy", 2345], "s65": ["game/script.rpy", 2355], "s66": ["game/script.rpy", 2385], "s67": ["game/script.rpy", 2387], "s68": ["game/script.rpy", 2389], "s69": ["game/script.rpy", 2391], "s70": ["game/script.rpy", 2393], "s71": ["game/script.rpy", 2395], "s72": ["game/script.rpy", 2397], "s73": ["game/script.rpy", 2399], "s74": ["game/script.rpy", 2401], "s75": ["game/script.rpy", 2403], "s76": ["game/script.rpy", 2405], "s77": ["game/script.rpy", 2407], "s78": ["game/script.rpy", 2409], "s79": ["game/script.rpy", 2411], "s80": ["game/script.rpy", 2413], "s81": ["game/script.rpy", 2415], "s82": ["game/script.rpy", 2417], "s83": ["game/script.rpy", 2419], "s84": ["game/script.rpy", 2421], "s85": ["game/script.rpy", 2423], "s86": ["game/script.rpy", 2425], "s87": ["game/script.rpy", 2427], "s88": ["game/script.rpy", 2429], "s89": ["game/script.rpy", 2431], "s90": ["game/script.rpy", 2433], "s91": ["game/script.rpy", 2435], "s92": ["game/script.rpy", 2437], "e0": ["game/script.rpy", 2439], "e1": ["game/script.rpy", 2441], "e2": ["game/script.rpy", 2443], "e3": ["game/script.rpy", 2445], "e4": ["game/script.rpy", 2447], "e5": ["game/script.rpy", 2449], "e6": ["game/script.rpy", 2451], "e7": ["game/script.rpy", 2453], "e8": ["game/script.rpy", 2455], "e9": ["game/script.rpy", 2457], "e10": ["game/script.rpy", 2459], "e11": ["game/script.rpy", 2461], "e12": ["game/script.rpy", 2463], "e13": ["game/script.rpy", 2465]}, "define": {}, "screen": {}, "transform": {}, "callable": {}}}